clipmorpher/__init__.py
clipmorpher/app.py
clipmorpher/clipMorpher.py
clipmorpher/dataLoader.py
clipmorpher/file.py
clipmorpher/loss.py
clipmorpher/talkNet.py
clipmorpher/test.py
clipmorpher/trainTalkNet.py
clipmorpher/videoUtils/__init__.py
clipmorpher/videoUtils/video_utils.py
OmniMorpher-2.1.dist-info/METADATA
OmniMorpher-2.1.dist-info/WHEEL
OmniMorpher-2.1.dist-info/top_level.txt
OmniMorpher-2.1.dist-info/RECORD
