Metadata-Version: 2.1
Name: OmniMorpher
Version: 2.1
Summary: OmniMorpher - Code based video editor
Author: Hanan Basheer
Author-email: hanan.basheer@iitb.ac.in
Keywords: python,OmniMorpher,video,editor
Classifier: Development Status :: 3 - Alpha
Classifier: Intended Audience :: Education
Classifier: Programming Language :: Python :: 2
Classifier: Programming Language :: Python :: 3
Classifier: Operating System :: MacOS :: MacOS X
Classifier: Operating System :: Microsoft :: Windows
Requires-Dist: azure-storage-blob
Requires-Dist: fastapi
Requires-Dist: python-dotenv
Requires-Dist: uvicorn
Requires-Dist: moviepy
Requires-Dist: numpy
Requires-Dist: pydantic
Requires-Dist: imageio
Requires-Dist: torch
Requires-Dist: tqdm
Requires-Dist: opencv-python
Requires-Dist: python-speech-features
Requires-Dist: argparse
